LICENSE
README.md
setup.py
rusty_python_fib/__init__.py
rusty_python_fib.egg-info/PKG-INFO
rusty_python_fib.egg-info/SOURCES.txt
rusty_python_fib.egg-info/dependency_links.txt
rusty_python_fib.egg-info/entry_points.txt
rusty_python_fib.egg-info/requires.txt
rusty_python_fib.egg-info/top_level.txt
rusty_python_fib/cmd/__init__.py
rusty_python_fib/cmd/fib_numb.py
rusty_python_fib/fib_calcs/__init__.py
rusty_python_fib/fib_calcs/fib_number.py
rusty_python_fib/fib_calcs/fib_numbers.py
tests/rusty-python-fib/__init__.py
tests/rusty-python-fib/fib_calcs/__init__.py
tests/rusty-python-fib/fib_calcs/test_fib_number.py
tests/rusty-python-fib/fib_calcs/test_fib_numbers.py